PlatformoClient/__init__.py
PlatformoClient/base_broker.py
PlatformoClient/dict_broker.py
PlatformoClient/monitor_thread.py
PlatformoClient/uwsgi_cache_broker.py
PlatformoClient-0.0.7.dist-info/DESCRIPTION.rst
PlatformoClient-0.0.7.dist-info/METADATA
PlatformoClient-0.0.7.dist-info/RECORD
PlatformoClient-0.0.7.dist-info/WHEEL
PlatformoClient-0.0.7.dist-info/metadata.json
PlatformoClient-0.0.7.dist-info/top_level.txt
platform_monitor_client/__init__.py
platform_monitor_client/monitor_thread.py
